pyemg_cometa/__init__.py
pyemg_cometa/capture_configuration.py
pyemg_cometa/constants.py
pyemg_cometa/daq_system.py
pyemg_cometa/device_dependent_functionalities.py
pyemg_cometa/event_args.py
pyemg_cometa/foot_sw_transducer.py
pyemg_cometa/sensor_configuration.py
pyemg_cometa/version.py
pyemg_cometa/lib/CyUSB.dll
pyemg_cometa/lib/Waveplus.DaqSys.dll
pyemg_cometa/lib/Waveplus.DaqSysInterface.dll
pysio_pyemg_cometa-0.0.1.dist-info/licenses/LICENSE
pysio_pyemg_cometa-0.0.1.dist-info/METADATA
pysio_pyemg_cometa-0.0.1.dist-info/WHEEL
pysio_pyemg_cometa-0.0.1.dist-info/top_level.txt
pysio_pyemg_cometa-0.0.1.dist-info/RECORD
