Metadata-Version: 2.4
Name: pysio-pyemg-cometa
Version: 0.0.1
Summary: A pythonic wrapper library for Cometa sEMG Waveplus devices
Author: e-Media Research Lab @ KU Leuven
Author-email: Maxim Yudayev <maxim.yudayev@gmail.com>
License-Expression: MIT
Project-URL: Repository, https://github.com/maximyudayev/pyemg-cometa.git
Project-URL: Issues, https://github.com/maximyudayev/pyemg-cometa/issues
Project-URL: Changelog, https://github.com/maximyudayev/pyemg-cometa/blob/main/CHANGELOG.md
Keywords: wearables,sensors,surface electromyography,cometa,streaming,sensing,physiology
Platform: win32
Platform: win-amd64
Classifier: Programming Language :: Python :: 3
Classifier: Operating System :: Microsoft :: Windows
Classifier: Development Status :: 4 - Beta
Classifier: Intended Audience :: Healthcare Industry
Classifier: Intended Audience :: Education
Classifier: Intended Audience :: Developers
Classifier: Intended Audience :: Science/Research
Classifier: Topic :: Scientific/Engineering
Classifier: Topic :: Scientific/Engineering :: Medical Science Apps.
Requires-Python: >=3.7
License-File: LICENSE
Requires-Dist: pythonnet
Dynamic: license-file
